pyrencode/__init__.py
pyrencode/constants.py
pyrencode/decode.py
pyrencode/encode.py
pyrencode/py.typed
pyrencode/utils.py
pyrencode-0.3.0.dist-info/LICENSE.md
pyrencode-0.3.0.dist-info/METADATA
pyrencode-0.3.0.dist-info/WHEEL
pyrencode-0.3.0.dist-info/RECORD
