Metadata-Version: 2.3
Name: pyrencode
Version: 0.3.0
Summary: A pure python rencoder
Home-page: https://pyrencode.readthedocs.io/en/stable/
License: BSD-3-Clause
Keywords: encoding
Author: Stephanos Kuma
Author-email: "Stephanos Kuma" <stephanos@kuma.ai>
Requires-Python: >=3.9
Classifier: Development Status :: 5 - Production/Stable
Classifier: Intended Audience :: Developers
Classifier: License :: OSI Approved :: BSD License
Classifier: Operating System :: OS Independent
Classifier: Programming Language :: Python :: 3 :: Only
Requires-Dist: pyutilkit (~=0.6)
Project-URL: Documentation, https://pyrencode.readthedocs.io/en/stable/
Project-URL: Repository, https://github.com/spapanik/pyrencode
